swarmauri_certservice_gcpkms/GcpKmsCertService.py
swarmauri_certservice_gcpkms/__init__.py
swarmauri_certservice_gcpkms-0.2.0.dev4.dist-info/LICENSE
swarmauri_certservice_gcpkms-0.2.0.dev4.dist-info/METADATA
swarmauri_certservice_gcpkms-0.2.0.dev4.dist-info/WHEEL
swarmauri_certservice_gcpkms-0.2.0.dev4.dist-info/entry_points.txt
swarmauri_certservice_gcpkms-0.2.0.dev4.dist-info/RECORD
