Metadata-Version: 2.3
Name: swarmauri_certservice_gcpkms
Version: 0.2.0.dev4
Summary: Google Cloud KMS Certificate Service for Swarmauri
License: Apache-2.0
Author: Swarmauri
Author-email: opensource@swarmauri.com
Requires-Python: >=3.10,<3.13
Classifier: License :: OSI Approved :: Apache Software License
Classifier: Programming Language :: Python :: 3.10
Classifier: Programming Language :: Python :: 3.11
Classifier: Programming Language :: Python :: 3.12
Provides-Extra: gcp
Requires-Dist: cryptography
Requires-Dist: google-cloud-kms ; extra == "gcp"
Requires-Dist: swarmauri_base
Requires-Dist: swarmauri_core
Requires-Dist: swarmauri_standard
